Sequential Circuits/Universal Shift Register/universal_shift_register.v
module universal_shift_register (
    input clk,
    input rst,
    input [1:0] sel,
    input [3:0] pdata,   // parallel data input
    input sin_l,         // serial input for shift left
    input sin_r,         // serial input for shift right
    output reg [3:0] q
);

always @(posedge clk or posedge rst) begin
    if (rst)
        q <= 4'b0000;
    else begin
        case (sel)
            2'b00: q <= q;                         // Hold
            2'b01: q <= {sin_r, q[3:1]};           // Shift Right
            2'b10: q <= {q[2:0], sin_l};           // Shift Left
            2'b11: q <= pdata;                     // Parallel Load
            default: q <= q;
        endcase
    end
end

endmodule

Sequential Circuits/Universal Shift Register/tb_universal_shift_register.v
module tb_universal_shift_register;

reg clk, rst;
reg [1:0] sel;
reg [3:0] pdata;
reg sin_l, sin_r;
wire [3:0] q;

universal_shift_register dut (
    .clk(clk),
    .rst(rst),
    .sel(sel),
    .pdata(pdata),
    .sin_l(sin_l),
    .sin_r(sin_r),
    .q(q)
);

// Clock generation
always #5 clk = ~clk;

initial begin
    $dumpfile("universal_shift_register.vcd");
    $dumpvars(0, tb_universal_shift_register);

    clk = 0;
    rst = 1;
    sel = 2'b00;
    pdata = 4'b0000;
    sin_l = 0;
    sin_r = 0;

    #10 rst = 0;

    // Parallel Load
    #10 sel = 2'b11; pdata = 4'b1010;

    // Hold
    #10 sel = 2'b00;

    // Shift Right
    #10 sel = 2'b01; sin_r = 1;
    #10 sin_r = 0;

    // Shift Left
    #10 sel = 2'b10; sin_l = 1;
    #10 sin_l = 0;

    // Hold again
    #10 sel = 2'b00;

    #20 $finish;
end

endmodule

Sequential Circuits/Universal Shift Register/universal_shift_register.vcd
$date
	Fri Jan 16 15:55:06 2026
$end
$version
	Icarus Verilog
$end
$timescale
	1s
$end
$scope module tb_universal_shift_register $end
$var wire 4 ! q [3:0] $end
$var reg 1 " clk $end
$var reg 4 # pdata [3:0] $end
$var reg 1 $ rst $end
$var reg 2 % sel [1:0] $end
$var reg 1 & sin_l $end
$var reg 1 ' sin_r $end
$scope module dut $end
$var wire 1 " clk $end
$var wire 4 ( pdata [3:0] $end
$var wire 1 $ rst $end
$var wire 2 ) sel [1:0] $end
$var wire 1 & sin_l $end
$var wire 1 ' sin_r $end
$var reg 4 * q [3:0] $end
$upscope $end
$upscope $end
$enddefinitions $end
$comment Show the parameter values. $end
$dumpall
$end
#0
$dumpvars
b0 *
b0 )
b0 (
0'
0&
b0 %
1$
b0 #
0"
b0 !
$end
#5
1"
#10
0"
0$
#15
1"
#20
0"
b1010 #
b1010 (
b11 %
b11 )
#25
b1010 !
b1010 *
1"
#30
0"
b0 %
b0 )
#35
1"
#40
0"
1'
b1 %
b1 )
#45
b1101 !
b1101 *
1"
#50
0"
0'
#55
b110 !
b110 *
1"
#60
0"
1&
b10 %
b10 )
#65
b1101 !
b1101 *
1"
#70
0"
0&
#75
b1010 !
b1010 *
1"
#80
0"
b0 %
b0 )
