Combinational Circuits/demux/demux.v
//1x4 demux is designed using verilog hdl 
module demux(output reg y0,y1,y2,y3,input [1:0]sel,input i);
always@(*) begin
    case(sel)
    2'h0: {y0,y1,y2,y3} = {i,3'b0};
     2'h1: {y0,y1,y2,y3} = {1'b0,i,2'b0};
      2'h2: {y0,y1,y2,y3} = {2'b0,i,1'b0};
       2'h3: {y0,y1,y2,y3} = {3'b0,i};
       default:$display("illegal sel type");
    endcase
end
endmodule

Combinational Circuits/demux/tb_demux.v
`timescale 1ns/1ps
module tb_demux();
reg [1:0] sel;
reg i;
wire y0,y1,y2,y3;
demux tb_demux(y0,y1,y2,y3,sel,i);
initial begin
    $dumpfile("demux.vcd");
    $dumpvars(0,tb_demux);
end
initial  begin
    sel=2'b00; i=0; #1;
    sel=2'b00; i=1; #1;
    sel=2'b01; i=0; #1;
    sel=2'b01; i=1; #1;
    sel=2'b10; i=0; #1;
    sel=2'b10; i=1; #1;
    sel=2'b11; i=0; #1;
    sel=2'b11; i=1; #1;
end
endmodule

Combinational Circuits/demux/demux.vcd
$date
	Mon Jan 12 14:47:58 2026
$end
$version
	Icarus Verilog
$end
$timescale
	1ps
$end
$scope module tb_demux $end
$scope module tb_demux $end
$var wire 1 ! i $end
$var wire 2 " sel [1:0] $end
$var reg 1 # y0 $end
$var reg 1 $ y1 $end
$var reg 1 % y2 $end
$var reg 1 & y3 $end
$upscope $end
$upscope $end
$enddefinitions $end
$comment Show the parameter values. $end
$dumpall
$end
#0
$dumpvars
0&
0%
0$
0#
b0 "
0!
$end
#1000
1#
1!
#2000
0#
0!
b1 "
#3000
1$
1!
#4000
0$
0!
b10 "
#5000
1%
1!
#6000
0%
0!
b11 "
#7000
1&
1!
