fulladder/fulladder.v
module fulladder(
    input a,b,cin,
    output reg sum,cout);
    always@(*) begin
        sum = a^b^cin;
        cout = (a&b)|(a&cin)|(b&cin);
    end
endmodule

fulladder/tb_fulladder.v
`timescale 1ns/1ps
module tb_fulladder();
reg A,B,CIN;
wire SUM,COUT;
fulladder dut(A,B,CIN,SUM,COUT);
initial begin 
    $dumpfile("full_adder.vcd");
    $dumpvars(1,tb_fulladder);
    #5;
    A = 0; B = 0; CIN = 0;
    #5;
    A = 0; B = 0; CIN = 1;
    #5;
    A = 0; B = 1; CIN = 0;
    #5;
    A = 0; B = 1; CIN = 1;
    #5;
    A = 1; B = 0; CIN = 0;
    #5;
    A = 1; B = 0; CIN = 1;
    #5;
    A = 1; B = 1; CIN = 0;
    #5;
    A = 1; B = 1; CIN = 1;
    #5;
    $finish;
    end
 endmodule

fulladder/full_adder.vcd
$date
	Mon Sep  8 10:46:25 2025
$end
$version
	Icarus Verilog
$end
$timescale
	1ps
$end
$scope module tb_fulladder $end
$var wire 1 ! SUM $end
$var wire 1 " COUT $end
$var reg 1 # A $end
$var reg 1 $ B $end
$var reg 1 % CIN $end
$upscope $end
$enddefinitions $end
$comment Show the parameter values. $end
$dumpall
$end
#0
$dumpvars
x%
x$
x#
x"
x!
$end
#5000
0"
0!
0%
0$
0#
#10000
1!
1%
#15000
0%
1$
#20000
1"
0!
1%
#25000
0"
1!
0%
0$
1#
#30000
1"
0!
1%
#35000
0%
1$
#40000
1!
1%
