Combinational Circuits/decoder/decoder.v
//2x4 decoder
module decoder(output reg [7:0]y,input [2:0]i);

always@(i) begin
    y = 8'b0;
    case(i)
    3'b000: y = {7'b0,1'b1};
    3'b001:y = {6'b0,1'b1,1'b0};
    3'b010:y= {5'b0,1'b1,2'b0};
    3'b011:y = {4'b0,1'b1,3'b0};
    3'b100: y = {3'b0,1'b1,4'b0};
    3'b101:y = {2'b0,1'b1,5'b0};
    3'b110:y = {1'b0,1'b1,6'b0};
    3'b111:y = {1'b1,7'b0};
    default: y = 0;
    endcase
end

endmodule

Combinational Circuits/decoder/tb_decoder.v
module tb_decoder();
reg [2:0]i;
wire [7:0]y;
decoder tb_decoder(y,i);
initial begin
    $dumpfile("decoder.vcd");
    $dumpvars(0,tb_decoder);
end   
initial begin
#5; i = 000;
#5; i = 001;
#5; i = 010;
#5; i = 011;
#5; i = 100;
#5; i = 101;
#5; i = 110;
#5; i = 111;

$finish();
end
endmodule

Combinational Circuits/decoder/decoder.vcd
$date
	Mon Jan 12 21:50:11 2026
$end
$version
	Icarus Verilog
$end
$timescale
	1s
$end
$scope module tb_decoder $end
$scope module tb_decoder $end
$var wire 3 ! i [2:0] $end
$var reg 8 " y [7:0] $end
$upscope $end
$upscope $end
$enddefinitions $end
$comment Show the parameter values. $end
$dumpall
$end
#0
$dumpvars
bx "
bx !
$end
#5
b1 "
b0 !
#10
b10 "
b1 !
#15
b100 "
b10 !
#20
b1000 "
b11 !
#25
b10000 "
b100 !
#30
b100000 "
b101 !
#35
b1000000 "
b110 !
#40
b10000000 "
b111 !
