Combinational Circuits/full_adder/halfadder.v
module halfadder(output sum,carry,input a,b);
assign sum = a ^ b;
assign carry = a & b;
endmodule

Combinational Circuits/full_adder/fulladder.v
//The full adder is implemented using two half adders

module fulladder(output sum,carry,input a,b,cin);
wire sum1,carry1,carry2;
halfadder ha1 (sum1,carry1,a,b);
halfadder ha2 (sum,carry2,sum1,cin);
assign carry = carry1 | carry2;

endmodule

Combinational Circuits/full_adder/tb_fulladder.v
`timescale 1ns/1ps
module tb_fulladder();
wire sum,carry;
reg a,b,cin;

fulladder tb_fulladder (sum,carry,a,b,cin);

initial begin
    $dumpfile("fulladder.vcd");
    $dumpvars(0,tb_fulladder);
end
initial begin
    #10;
    a = 0; b = 0; cin = 0;
    #10;
    a = 0; b = 0; cin = 1;
    #10;
    a = 0; b = 1; cin = 0;
    #10;
    a = 0; b = 1; cin = 1;
    #10;
    a = 1; b = 0; cin = 0;
    #10;
    a = 1; b = 0; cin = 1;
    #10;
    a = 1; b = 1; cin = 0;
    #10;
    a = 1; b = 1; cin = 1;
    #10;
    $finish;
end
endmodule

Combinational Circuits/full_adder/fulladder.vcd
$date
	Mon Jan 12 12:02:24 2026
$end
$version
	Icarus Verilog
$end
$timescale
	1ps
$end
$scope module tb_fulladder $end
$scope module tb_fulladder $end
$var wire 1 ! a $end
$var wire 1 " b $end
$var wire 1 # carry $end
$var wire 1 $ cin $end
$var wire 1 % sum1 $end
$var wire 1 & sum $end
$var wire 1 ' carry2 $end
$var wire 1 ( carry1 $end
$scope module ha1 $end
$var wire 1 ! a $end
$var wire 1 " b $end
$var wire 1 ( carry $end
$var wire 1 % sum $end
$upscope $end
$scope module ha2 $end
$var wire 1 % a $end
$var wire 1 $ b $end
$var wire 1 ' carry $end
$var wire 1 & sum $end
$upscope $end
$upscope $end
$upscope $end
$enddefinitions $end
$comment Show the parameter values. $end
$dumpall
$end
#0
$dumpvars
x(
x'
x&
x%
x$
x#
x"
x!
$end
#10000
0#
0&
0'
0%
0(
0$
0"
0!
#20000
1&
1$
#30000
1%
0$
1"
#40000
1#
0&
1'
1$
#50000
0#
1&
0'
0$
0"
1!
#60000
1#
0&
1'
1$
#70000
0'
0%
1(
0$
1"
#80000
1&
1$
