Combinational Circuits/encoder/priority encoder/priority_encoder.v
module priority_encoder(output reg [2:0]y, input [7:0]D);

always@(*) begin
    casex(D) 
        8'b1xxx_xxxx: y = 3'b111;
        8'b01xx_xxxx: y = 3'b110;
        8'b001x_xxxx: y = 3'b101;
        8'b0001_xxxx: y = 3'b100;
        8'b0000_1xxx: y = 3'b011;
        8'b0000_01xx: y = 3'b010;
        8'b0000_001x: y = 3'b001;
        8'b0000_0001: y = 3'b000;   
        default: $display("enter valid input");
    endcase
end
endmodule

Combinational Circuits/encoder/priority encoder/tb_priority_encoder.v
`timescale 1ns/1ps
module tb_priority_encoder();
reg [7:0]D;
wire [2:0]y;
priority_encoder tb_priority_encoder(y,D);
initial begin
    $dumpfile("priorityencoder.vcd");
    $dumpvars(0,tb_priority_encoder);
end
initial begin
    repeat(8) begin
        D = $random;
        #10;
    end
end
endmodule

Combinational Circuits/encoder/priority encoder/priorityencoder.vcd
$date
	Tue Jan 13 16:45:29 2026
$end
$version
	Icarus Verilog
$end
$timescale
	1ps
$end
$scope module tb_priority_encoder $end
$scope module tb_priority_encoder $end
$var wire 8 ! D [7:0] $end
$var reg 3 " y [2:0] $end
$upscope $end
$upscope $end
$enddefinitions $end
$comment Show the parameter values. $end
$dumpall
$end
#0
$dumpvars
b101 "
b100100 !
$end
#10000
b111 "
b10000001 !
#20000
b11 "
b1001 !
#30000
b110 "
b1100011 !
#40000
b11 "
b1101 !
#50000
b111 "
b10001101 !
#60000
b110 "
b1100101 !
#70000
b100 "
b10010 !
