Sequential Circuits/register4bit/dflipflop.v
//d flipflop with synchronous reset(active high )
module dflipflop(output reg q, input clk,rst,d);
always@(posedge clk) begin
    if(rst)
        q <= 0;
    else 
        q <= d;
end
endmodule

Sequential Circuits/register8bit/register8bit.v
module register8bit (
    output [7:0]q,
    input clk,rst,
    input [7:0]d
    
);

dflipflop dff1(q[0],clk,rst,d[0]);
dflipflop dff2(q[1],clk,rst,d[1]);
dflipflop dff3(q[2],clk,rst,d[2]);
dflipflop dff4(q[3],clk,rst,d[3]);
dflipflop dff5(q[4],clk,rst,d[4]);
dflipflop dff6(q[5],clk,rst,d[5]);
dflipflop dff7(q[6],clk,rst,d[6]);
dflipflop dff8(q[7],clk,rst,d[7]);
endmodule

Sequential Circuits/register8bit/tb_register8bit.v
module tb_register8bit();
wire [7:0]q;
reg clk,rst;
reg [7:0]d;
register8bit tb_register8bit(q,clk,rst,d);
initial begin
    $dumpfile("register8bit.vcd");
    $dumpvars(0,tb_register8bit);
end
always #5 clk = ~clk;
initial begin
    clk =0;

    rst = 1'b0;
    d = 1'b0;
    for(integer i = 0; i < 16;i = i + 1)
    begin
        d = i;
        #10;
    end
    #10;
    rst = 1; d = 4'b1010;
    #10 $finish;
end
endmodule

Sequential Circuits/register8bit/register8bit.vcd
$date
	Thu Jan 15 13:21:16 2026
$end
$version
	Icarus Verilog
$end
$timescale
	1s
$end
$scope module tb_register8bit $end
$scope module tb_register8bit $end
$var wire 1 ! clk $end
$var wire 8 " d [7:0] $end
$var wire 1 # rst $end
$var wire 8 $ q [7:0] $end
$scope module dff1 $end
$var wire 1 ! clk $end
$var wire 1 % d $end
$var wire 1 # rst $end
$var reg 1 & q $end
$upscope $end
$scope module dff2 $end
$var wire 1 ! clk $end
$var wire 1 ' d $end
$var wire 1 # rst $end
$var reg 1 ( q $end
$upscope $end
$scope module dff3 $end
$var wire 1 ! clk $end
$var wire 1 ) d $end
$var wire 1 # rst $end
$var reg 1 * q $end
$upscope $end
$scope module dff4 $end
$var wire 1 ! clk $end
$var wire 1 + d $end
$var wire 1 # rst $end
$var reg 1 , q $end
$upscope $end
$scope module dff5 $end
$var wire 1 ! clk $end
$var wire 1 - d $end
$var wire 1 # rst $end
$var reg 1 . q $end
$upscope $end
$scope module dff6 $end
$var wire 1 ! clk $end
$var wire 1 / d $end
$var wire 1 # rst $end
$var reg 1 0 q $end
$upscope $end
$scope module dff7 $end
$var wire 1 ! clk $end
$var wire 1 1 d $end
$var wire 1 # rst $end
$var reg 1 2 q $end
$upscope $end
$scope module dff8 $end
$var wire 1 ! clk $end
$var wire 1 3 d $end
$var wire 1 # rst $end
$var reg 1 4 q $end
$upscope $end
$upscope $end
$upscope $end
$enddefinitions $end
$comment Show the parameter values. $end
$dumpall
$end
#0
$dumpvars
x4
03
x2
01
x0
0/
x.
0-
x,
0+
x*
0)
x(
0'
x&
0%
bx $
0#
b0 "
0!
$end
#5
0&
0(
0*
0,
0.
00
02
b0 $
04
1!
#10
1%
0!
b1 "
#15
b1 $
1&
1!
#20
0%
1'
0!
b10 "
#25
0&
b10 $
1(
1!
#30
1%
0!
b11 "
#35
b11 $
1&
1!
#40
0%
0'
1)
0!
b100 "
#45
0&
0(
b100 $
1*
1!
#50
1%
0!
b101 "
#55
b101 $
1&
1!
#60
0%
1'
0!
b110 "
#65
0&
b110 $
1(
1!
#70
1%
0!
b111 "
#75
b111 $
1&
1!
#80
0%
0'
0)
1+
0!
b1000 "
#85
0&
0(
0*
b1000 $
1,
1!
#90
1%
0!
b1001 "
#95
b1001 $
1&
1!
#100
0%
1'
0!
b1010 "
#105
0&
b1010 $
1(
1!
#110
1%
0!
b1011 "
#115
b1011 $
1&
1!
#120
0%
0'
1)
0!
b1100 "
#125
0&
0(
b1100 $
1*
1!
#130
1%
0!
b1101 "
#135
b1101 $
1&
1!
#140
0%
1'
0!
b1110 "
#145
0&
b1110 $
1(
1!
#150
1%
0!
b1111 "
#155
b1111 $
1&
1!
#160
0!
#165
1!
#170
0%
0)
0!
b1010 "
1#
#175
0,
0*
0(
b0 $
0&
1!
