Combinational Circuits/encoder/binary encoder/binaryEncoder.v
module binaryEncoder(output  [2:0]y,input [7:0]d);


assign y[2] = d[4]|d[5]|d[6]|d[7];
assign y[1] = d[2] | d[3] | d[6] | d[7];
assign y[0] = d[1] | d[3] |d[5] | d[7];
endmodule

Combinational Circuits/encoder/binary encoder/tb_binaryEncoder.v
module tb_binaryEncoder();
wire [2:0]y;
reg [7:0]d;
binaryEncoder tb_binaryEncoder(y,d);
initial begin
    $dumpfile("binary_encoder.vcd");
    $dumpvars(0,tb_binaryEncoder);
end
initial begin
    d = 8'b1;#10;
    for(integer i = 0 ; i < 8; i = i + 1)
    begin
        d = d<<1;
        #10;
    end
end
endmodule

Combinational Circuits/encoder/binary encoder/binary_encoder.vcd
$date
	Mon Jan 12 21:34:14 2026
$end
$version
	Icarus Verilog
$end
$timescale
	1s
$end
$scope module tb_binaryEncoder $end
$scope module tb_binaryEncoder $end
$var wire 8 ! d [7:0] $end
$var wire 3 " y [2:0] $end
$upscope $end
$upscope $end
$enddefinitions $end
$comment Show the parameter values. $end
$dumpall
$end
#0
$dumpvars
b0 "
b1 !
$end
#10
b1 "
b10 !
#20
b10 "
b100 !
#30
b11 "
b1000 !
#40
b100 "
b10000 !
#50
b101 "
b100000 !
#60
b110 "
b1000000 !
#70
b111 "
b10000000 !
#80
b0 "
b0 !
