Sequential Circuits/JK flipflop/jkflipflop.v
//jk flipflop with synchronous active low reset 
module jkflipflop(output reg q, output qbar,input j,k,clk,rst);
always@(posedge clk) begin
    if(!rst)
        q <= 0;
    else begin
        case({j,k})
            2'b00: q <= q; //hold
            2'b01: q <= 1'b0; //reset
            2'b10: q <= 1'b1; //set
            2'b11: q <= ~q; //toggle mode
        endcase
    end
end
assign qbar = ~q;
endmodule

Sequential Circuits/JK flipflop/tb_jkflipflop.v
module tb_jkflipflop();
wire q,qbar;
reg j,k,rst,clk;
jkflipflop tb_jkflipflop(q,qbar,j,k,clk,rst);

initial begin
    $dumpfile("jkflipflop.vcd");
    $dumpvars(0,tb_jkflipflop);
end
always #5 clk = ~clk;
initial begin
    clk = 0; 
    rst = 0; j = 1; k = 0;
    #10;
    rst = 0; j = 0;k = 1;
    #10;
    rst = 1;
    j = 0; k = 0;
    #10;
    j = 0; k = 1;
    #10;
    j = 1; k = 0;
    #10;
    j = 1; k =1;
    #30;
    $finish;
end
endmodule

Sequential Circuits/JK flipflop/jkflipflop.vcd
$date
	Thu Jan 15 11:33:57 2026
$end
$version
	Icarus Verilog
$end
$timescale
	1s
$end
$scope module tb_jkflipflop $end
$scope module tb_jkflipflop $end
$var wire 1 ! clk $end
$var wire 1 " j $end
$var wire 1 # k $end
$var wire 1 $ qbar $end
$var wire 1 % rst $end
$var reg 1 & q $end
$upscope $end
$upscope $end
$enddefinitions $end
$comment Show the parameter values. $end
$dumpall
$end
#0
$dumpvars
x&
0%
x$
0#
1"
0!
$end
#5
1$
0&
1!
#10
0!
1#
0"
#15
1!
#20
0!
0#
1%
#25
1!
#30
0!
1#
#35
1!
#40
0!
0#
1"
#45
0$
1&
1!
#50
0!
1#
#55
1$
0&
1!
#60
0!
#65
0$
1&
1!
#70
0!
#75
1$
0&
1!
