Sequential Circuits/T flipflop/t_flipflop.v
module t_flipflop(output reg q, output qbar, input t, clk, rst);
always @(posedge clk) begin
    if(!rst)             // active-low reset
        q <= 0;
    else
        q <= t ? ~q : q; // toggle if t=1
end

assign qbar = ~q;

endmodule

Sequential Circuits/T flipflop/tb_tflipflop.v
module tb_tflipflop();
wire q, qbar;
reg t, clk, rst;

t_flipflop dut(q, qbar, t, clk, rst);

always #5 clk = ~clk;   // 10 ns clock

initial begin
    clk = 0;            // IMPORTANT FIX
    rst = 0;
    t = 0;

    $dumpfile("tflipflop.vcd");
    $dumpvars(0, tb_tflipflop);

    // Test sequence
    #10 rst = 1; t = 0;   // normal hold
    #10 t = 1;            // toggle
    #10 t = 0;            // hold
    #10 t = 1;            // toggle
    #20;

    $finish;
end

endmodule

Sequential Circuits/T flipflop/tflipflop.vcd
$date
	Wed Jan 14 16:54:23 2026
$end
$version
	Icarus Verilog
$end
$timescale
	1s
$end
$scope module tb_tflipflop $end
$var wire 1 ! qbar $end
$var wire 1 " q $end
$var reg 1 # clk $end
$var reg 1 $ rst $end
$var reg 1 % t $end
$scope module dut $end
$var wire 1 # clk $end
$var wire 1 ! qbar $end
$var wire 1 $ rst $end
$var wire 1 % t $end
$var reg 1 " q $end
$upscope $end
$upscope $end
$enddefinitions $end
$comment Show the parameter values. $end
$dumpall
$end
#0
$dumpvars
0%
0$
0#
x"
x!
$end
#5
1!
0"
1#
#10
0#
1$
#15
1#
#20
0#
1%
#25
0!
1"
1#
#30
0#
0%
#35
1#
#40
0#
1%
#45
1!
0"
1#
#50
0#
#55
0!
1"
1#
