Sequential Circuits/synchronous_up_counter/syncronous_up_counter.v
`timescale 1ns / 1ps
module syncronous_up_counter(
    input clk,rst,
    output reg [2:0]count
    );
    always@(posedge clk) begin
       if(rst)
            count = 3'b000;
       else
           count = count + 1;
    end
endmodule

Sequential Circuits/synchronous_up_counter/tb_up_counter.v
`timescale 1ns / 1ps
module tb_up_counter();
reg clk,rst;
wire [2:0]count;
syncronous_up_counter tb_up_counter(.clk(clk),.rst(rst),.count(count));
always #5 clk = ~clk;
initial begin
clk = 0;
rst = 0;
#30;
rst = 1;
#30;
rst = 0;
#100 $finish;

end
initial begin
$dumpfile("upcounter.vcd");
$dumpvars(0,tb_up_counter);
end
endmodule

Sequential Circuits/synchronous_up_counter/upcounter.vcd
$date
	Mon Jan 19 15:25:55 2026
$end
$version
	Icarus Verilog
$end
$timescale
	1ps
$end
$scope module tb_up_counter $end
$scope module tb_up_counter $end
$var wire 1 ! clk $end
$var wire 1 " rst $end
$var reg 3 # count [2:0] $end
$upscope $end
$upscope $end
$enddefinitions $end
$comment Show the parameter values. $end
$dumpall
$end
#0
$dumpvars
bx #
0"
0!
$end
#5000
1!
#10000
0!
#15000
1!
#20000
0!
#25000
1!
#30000
0!
1"
#35000
b0 #
1!
#40000
0!
#45000
1!
#50000
0!
#55000
1!
#60000
0!
0"
#65000
b1 #
1!
#70000
0!
#75000
b10 #
1!
#80000
0!
#85000
b11 #
1!
#90000
0!
#95000
b100 #
1!
#100000
0!
#105000
b101 #
1!
#110000
0!
#115000
b110 #
1!
#120000
0!
#125000
b111 #
1!
#130000
0!
#135000
b0 #
1!
#140000
0!
#145000
b1 #
1!
#150000
0!
#155000
b10 #
1!
