Sequential Circuits/updowncounter/updown_counter.v
module updown_counter(output reg [3:0]count,input rst,clk,updown);
always @(posedge clk) begin
    if(rst)
        count <= 0;
    else if (updown) begin
        if(count == 15)
            count <= 0;
        else 
            count <= count + 1;
    end
    else begin
        if(count == 0)
            count <=15;
        else 
            count <= count - 1;
    end
end

endmodule

Sequential Circuits/updowncounter/tb_updowncounter.v
module tb_updowncounter();
wire [3:0]count;
reg clk,rst,updown;
updown_counter tb_updowncounter(count,rst,clk,updown);
initial begin
    $dumpfile("updowncounter.vcd");
    $dumpvars(0,tb_updowncounter);
end
always #5 clk = ~clk;
initial begin
    clk = 0;rst = 1;
    #20;
    rst = 0;
    updown = 1;
    #200;
    updown = 0;
    #200;
    rst = 1;
    #10;
    $finish;
end
initial begin
    $monitor($time,"count is %d",count);
end
endmodule

Sequential Circuits/updowncounter/updowncounter.vcd
$date
	Tue Jan 20 10:13:53 2026
$end
$version
	Icarus Verilog
$end
$timescale
	1s
$end
$scope module tb_updowncounter $end
$scope module tb_updowncounter $end
$var wire 1 ! clk $end
$var wire 1 " rst $end
$var wire 1 # updown $end
$var reg 4 $ count [3:0] $end
$upscope $end
$upscope $end
$enddefinitions $end
$comment Show the parameter values. $end
$dumpall
$end
#0
$dumpvars
bx $
x#
1"
0!
$end
#5
b0 $
1!
#10
0!
#15
1!
#20
0!
1#
0"
#25
b1 $
1!
#30
0!
#35
b10 $
1!
#40
0!
#45
b11 $
1!
#50
0!
#55
b100 $
1!
#60
0!
#65
b101 $
1!
#70
0!
#75
b110 $
1!
#80
0!
#85
b111 $
1!
#90
0!
#95
b1000 $
1!
#100
0!
#105
b1001 $
1!
#110
0!
#115
b1010 $
1!
#120
0!
#125
b1011 $
1!
#130
0!
#135
b1100 $
1!
#140
0!
#145
b1101 $
1!
#150
0!
#155
b1110 $
1!
#160
0!
#165
b1111 $
1!
#170
0!
#175
b0 $
1!
#180
0!
#185
b1 $
1!
#190
0!
#195
b10 $
1!
#200
0!
#205
b11 $
1!
#210
0!
#215
b100 $
1!
#220
0!
0#
#225
b11 $
1!
#230
0!
#235
b10 $
1!
#240
0!
#245
b1 $
1!
#250
0!
#255
b0 $
1!
#260
0!
#265
b1111 $
1!
#270
0!
#275
b1110 $
1!
#280
0!
#285
b1101 $
1!
#290
0!
#295
b1100 $
1!
#300
0!
#305
b1011 $
1!
#310
0!
#315
b1010 $
1!
#320
0!
#325
b1001 $
1!
#330
0!
#335
b1000 $
1!
#340
0!
#345
b111 $
1!
#350
0!
#355
b110 $
1!
#360
0!
#365
b101 $
1!
#370
0!
#375
b100 $
1!
#380
0!
#385
b11 $
1!
#390
0!
#395
b10 $
1!
#400
0!
#405
b1 $
1!
#410
0!
#415
b0 $
1!
#420
0!
1"
