Sequential Circuits/synchronous_down_counter/down_counter.v
module down_counter(output reg [2:0]count,input clk,rst);
always @(posedge clk ) begin
    if(rst)
        count = 15;
    else begin
            count = count - 1;
    end
end
endmodule

Sequential Circuits/synchronous_down_counter/tb_down_counter.v
module tb_down_counter();
wire [2:0]count;
reg clk,rst;
down_counter tb_down_counter(count,clk,rst);
initial begin
    $dumpfile("downcounter.vcd");
    $dumpvars(0,tb_down_counter);
end
always #5 clk = ~clk;
initial begin
    clk = 0;
    rst = 0;
    #30;
    rst = 1;
    #30;
    rst = 0;
    #200 $finish;
end

endmodule

Sequential Circuits/synchronous_down_counter/downcounter.vcd
$date
	Mon Jan 19 17:02:43 2026
$end
$version
	Icarus Verilog
$end
$timescale
	1s
$end
$scope module tb_down_counter $end
$scope module tb_down_counter $end
$var wire 1 ! clk $end
$var wire 1 " rst $end
$var reg 3 # count [2:0] $end
$upscope $end
$upscope $end
$enddefinitions $end
$comment Show the parameter values. $end
$dumpall
$end
#0
$dumpvars
bx #
0"
0!
$end
#5
1!
#10
0!
#15
1!
#20
0!
#25
1!
#30
0!
1"
#35
b111 #
1!
#40
0!
#45
1!
#50
0!
#55
1!
#60
0!
0"
#65
b110 #
1!
#70
0!
#75
b101 #
1!
#80
0!
#85
b100 #
1!
#90
0!
#95
b11 #
1!
#100
0!
#105
b10 #
1!
#110
0!
#115
b1 #
1!
#120
0!
#125
b0 #
1!
#130
0!
#135
b111 #
1!
#140
0!
#145
b110 #
1!
#150
0!
#155
b101 #
1!
#160
0!
#165
b100 #
1!
#170
0!
#175
b11 #
1!
#180
0!
#185
b10 #
1!
#190
0!
#195
b1 #
1!
#200
0!
#205
b0 #
1!
#210
0!
#215
b111 #
1!
#220
0!
#225
b110 #
1!
#230
0!
#235
b101 #
1!
#240
0!
#245
b100 #
1!
#250
0!
#255
b11 #
1!
